taskAI/__init__.py
taskAI/config.py
taskAI/agents/__init__.py
taskAI/agents/youtube_agent.py
taskAI/core/__init__.py
taskAI/core/llm_brain.py
taskAI/core/prompts.py
todoai-0.1.0.dist-info/METADATA
todoai-0.1.0.dist-info/WHEEL
todoai-0.1.0.dist-info/top_level.txt
todoai-0.1.0.dist-info/RECORD
