Metadata-Version: 2.4
Name: todoai
Version: 0.1.0
Summary: A Python library for AI tasks like YouTube summarization using Gemini
Home-page: https://github.com/yourusername/smartai
Author: Manush Sanchela
Author-email: Manush <manushsanchela796@email.com>
License: MIT
Keywords: youtube,gemini,langchain,summarizer,AI
Requires-Python: >=3.7
Requires-Dist: langchain
Requires-Dist: langchain-google-genai
Requires-Dist: phidata
Requires-Dist: youtube_transcript_api
Requires-Dist: python-dotenv
Dynamic: author
Dynamic: home-page
Dynamic: requires-python
